Metadata-Version: 2.1
Name: stensor
Version: 0.2.0
Summary: building deep learning framework
Home-page: https://gitee.com/ligan15/stensor
Author: ligan
Author-email: 623301032@qq.com
Classifier: Programming Language :: Python :: 3
Classifier: License :: OSI Approved :: Apache Software License
Classifier: Operating System :: OS Independent
Requires-Python: >=3.9
License-File: LICENSE
